message_loader/__init__.py
message_loader/msg_loader.py
message_loader-0.1.1.dist-info/METADATA
message_loader-0.1.1.dist-info/WHEEL
message_loader-0.1.1.dist-info/top_level.txt
message_loader-0.1.1.dist-info/RECORD
