Metadata-Version: 2.1
Name: message-loader
Version: 0.1.1
Summary: Basic Terminal Loading Message
Author: Wxlbr73 (Will Ward)
License: UNKNOWN
Keywords: python,threading,loading
Platform: UNKNOWN
Classifier: Development Status :: 1 - Planning
Classifier: Intended Audience :: Developers
Classifier: Programming Language :: Python :: 3
Classifier: Operating System :: Unix
Classifier: Operating System :: MacOS :: MacOS X
Classifier: Operating System :: Microsoft :: Windows
